shopware_api_client/__init__.py
shopware_api_client/base.py
shopware_api_client/cache.py
shopware_api_client/client.py
shopware_api_client/config.py
shopware_api_client/endpoints/__init__.py
shopware_api_client/endpoints/admin/__init__.py
shopware_api_client/endpoints/admin/commercial/__init__.py
shopware_api_client/endpoints/admin/commercial/b2b_components_role.py
shopware_api_client/endpoints/admin/commercial/b2b_components_shopping_list.py
shopware_api_client/endpoints/admin/commercial/b2b_components_shopping_list_line_item.py
shopware_api_client/endpoints/admin/commercial/b2b_employee.py
shopware_api_client/endpoints/admin/commercial/dynamic_access.py
shopware_api_client/endpoints/admin/core/__init__.py
shopware_api_client/endpoints/admin/core/acl_role.py
shopware_api_client/endpoints/admin/core/api_info.py
shopware_api_client/endpoints/admin/core/app.py
shopware_api_client/endpoints/admin/core/app_script_condition.py
shopware_api_client/endpoints/admin/core/category.py
shopware_api_client/endpoints/admin/core/cms_block.py
shopware_api_client/endpoints/admin/core/cms_page.py
shopware_api_client/endpoints/admin/core/cms_section.py
shopware_api_client/endpoints/admin/core/cms_slot.py
shopware_api_client/endpoints/admin/core/country.py
shopware_api_client/endpoints/admin/core/country_state.py
shopware_api_client/endpoints/admin/core/currency.py
shopware_api_client/endpoints/admin/core/currency_country_rounding.py
shopware_api_client/endpoints/admin/core/custom_entity.py
shopware_api_client/endpoints/admin/core/custom_field.py
shopware_api_client/endpoints/admin/core/customer.py
shopware_api_client/endpoints/admin/core/customer_address.py
shopware_api_client/endpoints/admin/core/customer_group.py
shopware_api_client/endpoints/admin/core/customer_recovery.py
shopware_api_client/endpoints/admin/core/customer_wishlist.py
shopware_api_client/endpoints/admin/core/customer_wishlist_product.py
shopware_api_client/endpoints/admin/core/delivery_time.py
shopware_api_client-1.1.4.dist-info/METADATA
shopware_api_client-1.1.4.dist-info/WHEEL
shopware_api_client-1.1.4.dist-info/licenses/LICENSE
shopware_api_client-1.1.4.dist-info/RECORD
