Metadata-Version: 2.4
Name: shopware-api-client
Version: 1.1.4
Summary:  An api client for the Shopware API
License: MIT
License-File: LICENSE
Keywords: shopware,api,client
Author: GWS Gesellschaft für Warenwirtschafts-Systeme mbH
Author-email: ebusiness@gws.ms
Requires-Python: >=3.12,<4.0
Classifier: License :: OSI Approved :: MIT License
Classifier: Operating System :: OS Independent
Classifier: Programming Language :: Python :: 3
Classifier: Programming Language :: Python :: 3.12
Classifier: Programming Language :: Python :: 3.13
Classifier: Programming Language :: Python :: 3.14
Provides-Extra: redis
Requires-Dist: httpx (>=0.28,<0.29)
Requires-Dist: httpx-auth (>=0.23,<0.24)
Requires-Dist: pydantic (>=2.6,<3.0)
Requires-Dist: pytest-random-order (>=1.1.1,<2.0.0)
Requires-Dist: redis (>5.0,<7.0) ; extra == "redis"
Project-URL: Bugtracker, https://github.com/GWS-mbH/shopware-api-client/issues
Project-URL: Changelog, https://github.com/GWS-mbH/shopware-api-client
Project-URL: Documentation, https://github.com/GWS-mbH/shopware-api-client/wiki
Project-URL: Homepage, https://github.com/GWS-mbH
Project-URL: Repository, https://github.com/GWS-mbH/shopware-api-client
